endless_sky/__init__.py
endless_sky/__main__.py
endless_sky/bindings.cpython-38-darwin.so
endless_sky/console.py
endless_sky/libpath_hack.py
endless_sky/loader.py
endless_sky/parser.py
endless_sky/endless-sky/source/AI.h
endless_sky/endless-sky/source/Account.h
endless_sky/endless-sky/source/Angle.h
endless_sky/endless-sky/source/Armament.h
endless_sky/endless-sky/source/AsteroidField.h
endless_sky/endless-sky/source/Audio.h
endless_sky/endless-sky/source/BankPanel.h
endless_sky/endless-sky/source/BatchDrawList.h
endless_sky/endless-sky/source/BatchShader.h
endless_sky/endless-sky/source/BoardingPanel.h
endless_sky/endless-sky/source/Body.h
endless_sky/endless-sky/source/CaptureOdds.h
endless_sky/endless-sky/source/CargoHold.h
endless_sky/endless-sky/source/CategoryTypes.h
endless_sky/endless-sky/source/ClickZone.h
endless_sky/endless-sky/source/CollisionSet.h
endless_sky/endless-sky/source/Color.h
endless_sky/endless-sky/source/Command.h
endless_sky/endless-sky/source/ConditionSet.h
endless_sky/endless-sky/source/Conversation.h
endless_sky/endless-sky/source/ConversationPanel.h
endless_sky/endless-sky/source/CoreStartData.h
endless_sky/endless-sky/source/DataFile.h
endless_sky/endless-sky/source/DataNode.h
endless_sky/endless-sky/source/DataWriter.h
endless_sky/endless-sky/source/Date.h
endless_sky/endless-sky/source/Depreciation.h
endless_sky/endless-sky/source/Dialog.h
endless_sky/endless-sky/source/Dictionary.h
endless_sky/endless-sky/source/DistanceMap.h
endless_sky/endless-sky/source/DrawList.h
endless_sky/endless-sky/source/Effect.h
endless_sky/endless-sky/source/Engine.h
endless_sky/endless-sky/source/EsUuid.h
endless_sky/endless-sky/source/EscortDisplay.h
endless_sky/endless-sky/source/File.h
endless_sky/endless-sky/source/Files.h
endless_sky/endless-sky/source/FillShader.h
endless_sky/endless-sky/source/Fleet.h
endless_sky/endless-sky/source/Flotsam.h
endless_sky/endless-sky/source/FogShader.h
endless_sky/endless-sky/source/FrameTimer.h
endless_sky_bindings-0.0.14.dist-info/METADATA
endless_sky_bindings-0.0.14.dist-info/WHEEL
endless_sky_bindings-0.0.14.dist-info/top_level.txt
endless_sky_bindings-0.0.14.dist-info/RECORD
