Metadata-Version: 2.1
Name: endless-sky-bindings
Version: 0.0.14
Summary: Python bindings for Endless Sky C++ code
Home-page: https://github.com/thomasballinger/endless-sky-bindings-python
Author: Thomas Ballinger
Author-email: thomasballinger@gmail.com
License: UNKNOWN
Platform: UNKNOWN
Provides-Extra: test
Requires-Dist: pytest ; extra == 'test'
